{
	"info": {
		"_postman_id": "2c26c34c-117b-42cf-8af9-dfb0ef72f2f2",
		"name": "Cliente",
		"schema": "https://schema.getpostman.com/json/collection/v2.1.0/collection.json"
	},
	"item": [
		{
			"name": "listarClientes",
			"request": {
				"auth": {
					"type": "basic",
					"basic": [
						{
							"key": "password",
							"value": "fb473a58-cdde-4cfc-8e4c-37135db15e18",
							"type": "string"
						},
						{
							"key": "username",
							"value": "user",
							"type": "string"
						}
					]
				},
				"method": "GET",
				"header": [],
				"url": {
					"raw": "http://localhost:8080/api/cliente/listar_clientes",
					"protocol": "http",
					"host": [
						"localhost"
					],
					"port": "8080",
					"path": [
						"api",
						"cliente",
						"listar_clientes"
					]
				}
			},
			"response": []
		},
		{
			"name": "crearClientes",
			"request": {
				"auth": {
					"type": "basic",
					"basic": [
						{
							"key": "password",
							"value": "fb473a58-cdde-4cfc-8e4c-37135db15e18",
							"type": "string"
						},
						{
							"key": "username",
							"value": "user",
							"type": "string"
						}
					]
				},
				"method": "POST",
				"header": [],
				"body": {
					"mode": "raw",
					"raw": "{\r\n    \"nombre\":\"post\",\r\n    \"apellidos\":\"man\",\r\n    \"identificacion\":\"id-postman\",\r\n    \"telefono\":\"12345678\"\r\n}",
					"options": {
						"raw": {
							"language": "json"
						}
					}
				},
				"url": {
					"raw": "http://localhost:8080/api/cliente/crear_clientes",
					"protocol": "http",
					"host": [
						"localhost"
					],
					"port": "8080",
					"path": [
						"api",
						"cliente",
						"crear_clientes"
					]
				}
			},
			"response": []
		},
		{
			"name": "listarClientesID",
			"request": {
				"auth": {
					"type": "basic",
					"basic": [
						{
							"key": "password",
							"value": "fb473a58-cdde-4cfc-8e4c-37135db15e18",
							"type": "string"
						},
						{
							"key": "username",
							"value": "user",
							"type": "string"
						}
					]
				},
				"method": "GET",
				"header": [],
				"url": {
					"raw": "http://localhost:8080/api/cliente/listar_clientes/6",
					"protocol": "http",
					"host": [
						"localhost"
					],
					"port": "8080",
					"path": [
						"api",
						"cliente",
						"listar_clientes",
						"6"
					]
				}
			},
			"response": []
		},
		{
			"name": "eliminarClientesID",
			"request": {
				"auth": {
					"type": "basic",
					"basic": [
						{
							"key": "password",
							"value": "fb473a58-cdde-4cfc-8e4c-37135db15e18",
							"type": "string"
						},
						{
							"key": "username",
							"value": "user",
							"type": "string"
						}
					]
				},
				"method": "DELETE",
				"header": [],
				"url": {
					"raw": "http://localhost:8080/api/cliente/destruir_cliente/6",
					"protocol": "http",
					"host": [
						"localhost"
					],
					"port": "8080",
					"path": [
						"api",
						"cliente",
						"destruir_cliente",
						"6"
					]
				}
			},
			"response": []
		},
		{
			"name": "editarclientes",
			"request": {
				"auth": {
					"type": "basic",
					"basic": [
						{
							"key": "password",
							"value": "fb473a58-cdde-4cfc-8e4c-37135db15e18",
							"type": "string"
						},
						{
							"key": "username",
							"value": "user",
							"type": "string"
						}
					]
				},
				"method": "PUT",
				"header": [],
				"body": {
					"mode": "raw",
					"raw": "{\r\n    \"idCliente\":\"6\",\r\n    \"nombre\":\"post\",\r\n    \"apellidos\":\"man\",\r\n    \"identificacion\":\"id-postman actualizado\",\r\n    \"telefono\":\"12345678\"\r\n}\r\n",
					"options": {
						"raw": {
							"language": "json"
						}
					}
				},
				"url": {
					"raw": "http://localhost:8080/api/cliente/editar_cliente",
					"protocol": "http",
					"host": [
						"localhost"
					],
					"port": "8080",
					"path": [
						"api",
						"cliente",
						"editar_cliente"
					]
				}
			},
			"response": []
		},
		{
			"name": "contarClientes",
			"request": {
				"auth": {
					"type": "basic",
					"basic": [
						{
							"key": "password",
							"value": "fb473a58-cdde-4cfc-8e4c-37135db15e18",
							"type": "string"
						},
						{
							"key": "username",
							"value": "user",
							"type": "string"
						}
					]
				},
				"method": "GET",
				"header": [],
				"url": {
					"raw": "http://localhost:8080/api/cliente/contar_clientes",
					"protocol": "http",
					"host": [
						"localhost"
					],
					"port": "8080",
					"path": [
						"api",
						"cliente",
						"contar_clientes"
					]
				}
			},
			"response": []
		}
	]
}